pylane/__init__.py
pylane/entry.py
pylane/core/__init__.py
pylane/core/exception.py
pylane/core/injector.py
pylane/shell/__init__.py
pylane/shell/help_functions.py
pylane/shell/inject.py
pylane/shell/ipython_embed.py
pylane/shell/proxy.py
pylane/shell/remote_shell.py
pylane/shell/shell.py
pylane/shell/sock.py
pylane-0.0.9.dist-info/LICENSE
pylane-0.0.9.dist-info/METADATA
pylane-0.0.9.dist-info/WHEEL
pylane-0.0.9.dist-info/entry_points.txt
pylane-0.0.9.dist-info/top_level.txt
pylane-0.0.9.dist-info/RECORD
