Metadata-Version: 2.1
Name: pylane
Version: 0.0.9
Summary: UNKNOWN
Home-page: https://github.com/NtesEyes/pylane
Author: valensc, Wu Xiao
Author-email: weidong1312@gmail.com, notgiven@gmail.com
License: UNKNOWN
Download-URL: https://github.com/NtesEyes/pylane/archive/0.0.2.tar.gz
Keywords: debug,attach,gdb,shell
Platform: UNKNOWN
